acunetix/__init__.py
acunetix/__main__.py
acunetix/errors.py
acunetix/status_codes.py
acunetix/typehints.py
acunetix/utils.py
acunetix/methods/__init__.py
acunetix/methods/reports.py
acunetix/methods/scans.py
acunetix/methods/targets.py
acunetix/methods/users.py
acunetix/schema/__init__.py
acunetix/schema/access_map.py
acunetix/schema/current_session.py
acunetix/schema/file_attachment.py
acunetix/schema/host.py
acunetix/schema/input_target.py
acunetix/schema/message.py
acunetix/schema/notification.py
acunetix/schema/notification_data.py
acunetix/schema/report.py
acunetix/schema/report_template.py
acunetix/schema/scan.py
acunetix/schema/scan_profile.py
acunetix/schema/scan_speed.py
acunetix/schema/scheduling_options.py
acunetix/schema/status_statistic_entry.py
acunetix/schema/status_statistics.py
acunetix/schema/target.py
acunetix/schema/target_host_info.py
acunetix/schema/target_info.py
acunetix/schema/typed_list.py
acunetix/schema/user.py
acunetix/schema/vulnerability.py
acunetix/schema/web_scan_status.py
acunetix/schema/web_vulnerability_scanner.py
acunetix-0.0.7.dist-info/LICENSE
acunetix-0.0.7.dist-info/METADATA
acunetix-0.0.7.dist-info/WHEEL
acunetix-0.0.7.dist-info/top_level.txt
acunetix-0.0.7.dist-info/RECORD
